hello.py
rapidapi-0.0.0.dist-info/METADATA
rapidapi-0.0.0.dist-info/WHEEL
rapidapi-0.0.0.dist-info/top_level.txt
rapidapi-0.0.0.dist-info/RECORD
