Metadata-Version: 2.2
Name: rapidapi
Version: 0.0.0
Summary: a standardized application layout for fastapi with dynamic configuration support
Requires-Python: >=3.13
